{
  "data": {
    "article": {},
    "attachments": {
      "media_keys": [
        "3_1985745715264700417"
      ]
    },
    "author_id": "1546431985086009344",
    "conversation_id": "1985745717378654408",
    "created_at": "2025-11-04T16:27:27.000Z",
    "edit_controls": {
      "editable_until": "2025-11-04T17:27:27.000Z",
      "edits_remaining": 5,
      "is_edit_eligible": true
    },
    "edit_history_tweet_ids": [
      "1985745717378654408"
    ],
    "entities": {
      "urls": [
        {
          "display_url": "pic.x.com/diPa5aEX20",
          "end": 64,
          "expanded_url": "https://x.com/NL8526/status/1985745717378654408/photo/1",
          "media_key": "3_1985745715264700417",
          "start": 41,
          "url": "https://t.co/diPa5aEX20"
        }
      ]
    },
    "geo": {},
    "id": "1985745717378654408",
    "lang": "zh",
    "note_tweet": {
      "entities": {}
    },
    "possibly_sensitive": false,
    "public_metrics": {
      "bookmark_count": 0,
      "impression_count": 0,
      "like_count": 0,
      "quote_count": 0,
      "reply_count": 0,
      "retweet_count": 0
    },
    "reply_settings": "everyone",
    "text": "е®ӨеҸӢдҫқз„¶еҫҲеҗөе‘ў...зҢ«зҢ«е–ңж¬ўе®үйқҷзҡ„зҺҜеўғ еҘҪйҡҫ...еҗөеҫ—еҝ«з–ҜжҺү\nд»ҠеӨ© дёҖд»Ҫе·§е…ӢеҠӣрҹҚ« https://t.co/diPa5aEX20"
  },
  "includes": {
    "media": [
      {
        "height": 922,
        "media_key": "3_1985745715264700417",
        "public_metrics": {},
        "type": "photo",
        "url": "https://pbs.twimg.com/media/G47JNQSbQAEVT69.jpg",
        "width": 2048
      }
    ],
    "tweets": [
      {
        "article": {},
        "attachments": {
          "media_keys": [
            "3_1985745715264700417"
          ]
        },
        "author_id": "1546431985086009344",
        "conversation_id": "1985745717378654408",
        "created_at": "2025-11-04T16:27:27.000Z",
        "edit_controls": {
          "editable_until": "2025-11-04T17:27:27.000Z",
          "edits_remaining": 5,
          "is_edit_eligible": true
        },
        "edit_history_tweet_ids": [
          "1985745717378654408"
        ],
        "entities": {
          "urls": [
            {
              "display_url": "pic.x.com/diPa5aEX20",
              "end": 64,
              "expanded_url": "https://x.com/NL8526/status/1985745717378654408/photo/1",
              "media_key": "3_1985745715264700417",
              "start": 41,
              "url": "https://t.co/diPa5aEX20"
            }
          ]
        },
        "geo": {},
        "id": "1985745717378654408",
        "lang": "zh",
        "note_tweet": {
          "entities": {}
        },
        "possibly_sensitive": false,
        "public_metrics": {
          "bookmark_count": 0,
          "impression_count": 0,
          "like_count": 0,
          "quote_count": 0,
          "reply_count": 0,
          "retweet_count": 0
        },
        "reply_settings": "everyone",
        "text": "е®ӨеҸӢдҫқз„¶еҫҲеҗөе‘ў...зҢ«зҢ«е–ңж¬ўе®үйқҷзҡ„зҺҜеўғ еҘҪйҡҫ...еҗөеҫ—еҝ«з–ҜжҺү\nд»ҠеӨ© дёҖд»Ҫе·§е…ӢеҠӣрҹҚ« https://t.co/diPa5aEX20"
      }
    ],
    "users": [
      {
        "created_at": "2022-07-11T09:51:43.000Z",
        "description": "CNрҹҮЁрҹҮі | 07MTFрҹҸіпёҸвҖҚвҡ§пёҸ | ж— иҜҒеҗ«зі–рҹҚҘ hrt25/10 |рҹ“ҚIPжҙӘеҹҺ еӨ§еӯҰеңЁиҜ» | з»ҸеёёеҮәзҺ°иәҜдҪ“еҢ–з—ҮзҠ¶жңӘзЎ®иҜҠ(жІЎзңӢиҝҮеҢ»з”ҹ) е®¶еўғеӣ°йҡҫ | дёҚod дёҚж”№еҲҖ? дёҚжҠҪзғҹ дёҚе–қй…’ | рҹҘ°йҹіжёё жҖ§ж јеҸӢеҘҪдҪҶжҳҜи¶…зә§зјәзҲұиҮӘеҚ‘зӨҫжҒҗжӮІи§ӮеҶ…иҖ—ж— жі•е’Ңи§ЈиҮӘе·ұе–өрҹҗұ е®іжҖ•зӮёжҹң е·ІиҜ»дёҚеӣһ | и°ўи°ўе…іжіЁпјҢдә’foз§ҒдҝЎж‘ёж‘ёрҹ«¶",
        "id": "1546431985086009344",
        "name": "жҹ еҮүрҹҸіпёҸвҖҚвҡ§пёҸрҹҚҘ",
        "profile_image_url": "https://pbs.twimg.com/profile_images/1982315591961616384/XOHEeGGT_normal.jpg",
        "protected": false,
        "public_metrics": {
          "followers_count": 22,
          "following_count": 21,
          "like_count": 20,
          "listed_count": 0,
          "media_count": 9,
          "tweet_count": 38
        },
        "username": "NL8526",
        "verified": false
      }
    ]
  }
}