{
  "data": {
    "article": {},
    "attachments": {},
    "author_id": "1546431985086009344",
    "context_annotations": [
      {
        "domain": {
          "description": "Categories within Brand Verticals that narrow down the scope of Brands",
          "id": "46",
          "name": "Business Taxonomy"
        },
        "entity": {
          "description": "Brands, companies, advertisers and every non-person handle with the profit intent related to Banks, Credit cards, Insurance, Investments, Stocks ",
          "id": "1557696848252391426",
          "name": "Financial Services Business"
        }
      },
      {
        "domain": {
          "description": "Categories within Brand Verticals that narrow down the scope of Brands",
          "id": "46",
          "name": "Business Taxonomy"
        },
        "entity": {
          "description": "Brands, companies, advertisers and every non-person handle with the profit intent related to softwares, apps, communication equipments, hardwares",
          "id": "1557697333571112960",
          "name": "Technology Business"
        }
      },
      {
        "domain": {
          "description": "Named people in the world like Nelson Mandela",
          "id": "10",
          "name": "Person"
        },
        "entity": {
          "description": "Elon Musk",
          "id": "808713037230157824",
          "name": "Elon Musk"
        }
      },
      {
        "domain": {
          "description": "Top level interests and hobbies groupings, like Food or Travel",
          "id": "65",
          "name": "Interests and Hobbies Vertical"
        },
        "entity": {
          "id": "781974596148793345",
          "name": "Business & finance"
        }
      },
      {
        "domain": {
          "description": "A grouping of interests and hobbies entities, like Novelty Food or Destinations",
          "id": "66",
          "name": "Interests and Hobbies Category"
        },
        "entity": {
          "description": "Leadership",
          "id": "857878777191211008",
          "name": "Leadership"
        }
      },
      {
        "domain": {
          "description": "A taxonomy of user interests. ",
          "id": "131",
          "name": "Unified Twitter Taxonomy"
        },
        "entity": {
          "description": "Elon Musk",
          "id": "808713037230157824",
          "name": "Elon Musk"
        }
      },
      {
        "domain": {
          "description": "A taxonomy of user interests. ",
          "id": "131",
          "name": "Unified Twitter Taxonomy"
        },
        "entity": {
          "description": "Tech Professionals",
          "id": "1091420346660470784",
          "name": "Tech personalities"
        }
      },
      {
        "domain": {
          "description": "A taxonomy of user interests. ",
          "id": "131",
          "name": "Unified Twitter Taxonomy"
        },
        "entity": {
          "id": "1166406108623163392",
          "name": "Business personalities"
        }
      }
    ],
    "conversation_id": "2066454139278901610",
    "created_at": "2026-06-15T10:15:37.000Z",
    "edit_controls": {
      "editable_until": "2026-06-15T11:15:37.000Z",
      "edits_remaining": 5,
      "is_edit_eligible": false
    },
    "edit_history_tweet_ids": [
      "2066464638930387361"
    ],
    "entities": {
      "mentions": [
        {
          "end": 15,
          "id": "2055911737208315904",
          "start": 0,
          "username": "omgnowihasfish"
        },
        {
          "end": 21,
          "id": "1720665183188922368",
          "start": 16,
          "username": "grok"
        },
        {
          "end": 37,
          "id": "44196397",
          "start": 28,
          "username": "elonmusk"
        }
      ]
    },
    "geo": {},
    "id": "2066464638930387361",
    "in_reply_to_user_id": "2055911737208315904",
    "lang": "zh",
    "note_tweet": {
      "entities": {}
    },
    "possibly_sensitive": false,
    "public_metrics": {
      "bookmark_count": 0,
      "impression_count": 0,
      "like_count": 0,
      "quote_count": 0,
      "reply_count": 0,
      "retweet_count": 0
    },
    "referenced_tweets": [
      {
        "id": "2066454139278901610",
        "type": "replied_to"
      }
    ],
    "reply_settings": "everyone",
    "text": "@omgnowihasfish @grok block @elonmusk会发生什么？"
  },
  "includes": {
    "media": [
      {
        "height": 2048,
        "media_key": "3_2066454136846184448",
        "public_metrics": {},
        "type": "photo",
        "url": "https://pbs.twimg.com/media/HK2FFsNacAA10bp.jpg",
        "width": 922
      }
    ],
    "tweets": [
      {
        "article": {},
        "attachments": {},
        "author_id": "1546431985086009344",
        "context_annotations": [
          {
            "domain": {
              "description": "Categories within Brand Verticals that narrow down the scope of Brands",
              "id": "46",
              "name": "Business Taxonomy"
            },
            "entity": {
              "description": "Brands, companies, advertisers and every non-person handle with the profit intent related to Banks, Credit cards, Insurance, Investments, Stocks ",
              "id": "1557696848252391426",
              "name": "Financial Services Business"
            }
          },
          {
            "domain": {
              "description": "Categories within Brand Verticals that narrow down the scope of Brands",
              "id": "46",
              "name": "Business Taxonomy"
            },
            "entity": {
              "description": "Brands, companies, advertisers and every non-person handle with the profit intent related to softwares, apps, communication equipments, hardwares",
              "id": "1557697333571112960",
              "name": "Technology Business"
            }
          },
          {
            "domain": {
              "description": "Named people in the world like Nelson Mandela",
              "id": "10",
              "name": "Person"
            },
            "entity": {
              "description": "Elon Musk",
              "id": "808713037230157824",
              "name": "Elon Musk"
            }
          },
          {
            "domain": {
              "description": "Top level interests and hobbies groupings, like Food or Travel",
              "id": "65",
              "name": "Interests and Hobbies Vertical"
            },
            "entity": {
              "id": "781974596148793345",
              "name": "Business & finance"
            }
          },
          {
            "domain": {
              "description": "A grouping of interests and hobbies entities, like Novelty Food or Destinations",
              "id": "66",
              "name": "Interests and Hobbies Category"
            },
            "entity": {
              "description": "Leadership",
              "id": "857878777191211008",
              "name": "Leadership"
            }
          },
          {
            "domain": {
              "description": "A taxonomy of user interests. ",
              "id": "131",
              "name": "Unified Twitter Taxonomy"
            },
            "entity": {
              "description": "Elon Musk",
              "id": "808713037230157824",
              "name": "Elon Musk"
            }
          },
          {
            "domain": {
              "description": "A taxonomy of user interests. ",
              "id": "131",
              "name": "Unified Twitter Taxonomy"
            },
            "entity": {
              "description": "Tech Professionals",
              "id": "1091420346660470784",
              "name": "Tech personalities"
            }
          },
          {
            "domain": {
              "description": "A taxonomy of user interests. ",
              "id": "131",
              "name": "Unified Twitter Taxonomy"
            },
            "entity": {
              "id": "1166406108623163392",
              "name": "Business personalities"
            }
          }
        ],
        "conversation_id": "2066454139278901610",
        "created_at": "2026-06-15T10:15:37.000Z",
        "edit_controls": {
          "editable_until": "2026-06-15T11:15:37.000Z",
          "edits_remaining": 5,
          "is_edit_eligible": false
        },
        "edit_history_tweet_ids": [
          "2066464638930387361"
        ],
        "entities": {
          "mentions": [
            {
              "end": 15,
              "id": "2055911737208315904",
              "start": 0,
              "username": "omgnowihasfish"
            },
            {
              "end": 21,
              "id": "1720665183188922368",
              "start": 16,
              "username": "grok"
            },
            {
              "end": 37,
              "id": "44196397",
              "start": 28,
              "username": "elonmusk"
            }
          ]
        },
        "geo": {},
        "id": "2066464638930387361",
        "in_reply_to_user_id": "2055911737208315904",
        "lang": "zh",
        "note_tweet": {
          "entities": {}
        },
        "possibly_sensitive": false,
        "public_metrics": {
          "bookmark_count": 0,
          "impression_count": 0,
          "like_count": 0,
          "quote_count": 0,
          "reply_count": 0,
          "retweet_count": 0
        },
        "referenced_tweets": [
          {
            "id": "2066454139278901610",
            "type": "replied_to"
          }
        ],
        "reply_settings": "everyone",
        "text": "@omgnowihasfish @grok block @elonmusk会发生什么？"
      },
      {
        "article": {},
        "attachments": {
          "media_keys": [
            "3_2066454136846184448"
          ]
        },
        "author_id": "2055911737208315904",
        "conversation_id": "2066454139278901610",
        "created_at": "2026-06-15T09:33:54.000Z",
        "edit_controls": {
          "editable_until": "2026-06-15T10:33:54.000Z",
          "edits_remaining": 5,
          "is_edit_eligible": true
        },
        "edit_history_tweet_ids": [
          "2066454139278901610"
        ],
        "entities": {
          "urls": [
            {
              "display_url": "pic.x.com/wNFdonFIku",
              "end": 31,
              "expanded_url": "https://x.com/omgnowihasfish/status/2066454139278901610/photo/1",
              "media_key": "3_2066454136846184448",
              "start": 8,
              "url": "https://t.co/wNFdonFIku"
            }
          ]
        },
        "geo": {},
        "id": "2066454139278901610",
        "lang": "zh",
        "note_tweet": {
          "entities": {}
        },
        "possibly_sensitive": false,
        "public_metrics": {
          "bookmark_count": 0,
          "impression_count": 25,
          "like_count": 2,
          "quote_count": 0,
          "reply_count": 1,
          "retweet_count": 0
        },
        "reply_settings": "everyone",
        "text": "已封鎖斐濟杯子 https://t.co/wNFdonFIku"
      }
    ],
    "users": [
      {
        "created_at": "2022-07-11T09:51:43.000Z",
        "description": "🏳️‍⚧️07MTF ♍ISFP-T 😺AuDHD BPD 🎹钢专/数码/音游/MC 😴大一休学/家长不管党/不线下/小透明/友好欢迎dm ✨本人照片在亮点 🩷同类蓝v互fo 🙏抽象致歉 无故之b必回 ⬇️匿名问答箱",
        "entities": {
          "url": {
            "urls": [
              {
                "display_url": "ngl.link/nl8526",
                "end": 23,
                "expanded_url": "https://ngl.link/nl8526",
                "start": 0,
                "url": "https://t.co/jWEGQcvXbV"
              }
            ]
          }
        },
        "id": "1546431985086009344",
        "name": "柠凉🍥🏳️‍⚧️",
        "pinned_tweet_id": "2066003299510464743",
        "profile_image_url": "https://pbs.twimg.com/profile_images/2027271602556297216/MVm2kNIq_normal.jpg",
        "protected": false,
        "public_metrics": {
          "followers_count": 2682,
          "following_count": 790,
          "like_count": 16862,
          "listed_count": 4,
          "media_count": 155,
          "tweet_count": 705
        },
        "url": "https://t.co/jWEGQcvXbV",
        "username": "NL8526",
        "verified": true
      },
      {
        "created_at": "2026-05-17T07:23:39.000Z",
        "description": "座標台灣台中市 \n2009/12/24",
        "entities": {
          "url": {
            "urls": [
              {
                "display_url": "youtu.be/dQw4w9WgXcQ?si…",
                "end": 23,
                "expanded_url": "https://youtu.be/dQw4w9WgXcQ?si=Gnc7ktA0TsADpGRe",
                "start": 0,
                "url": "https://t.co/FZ1JCwuotB"
              }
            ]
          }
        },
        "id": "2055911737208315904",
        "location": "台中市, 台灣",
        "name": "黃瓜🍥",
        "profile_image_url": "https://pbs.twimg.com/profile_images/2055912532402216960/jnl7BbH6_normal.jpg",
        "protected": false,
        "public_metrics": {
          "followers_count": 1272,
          "following_count": 564,
          "like_count": 2473,
          "listed_count": 2,
          "media_count": 152,
          "tweet_count": 583
        },
        "url": "https://t.co/FZ1JCwuotB",
        "username": "omgnowihasfish",
        "verified": false
      },
      {
        "created_at": "2023-11-04T04:52:34.000Z",
        "description": "@grok it",
        "entities": {
          "description": {
            "mentions": [
              {
                "end": 5,
                "start": 0,
                "username": "grok"
              }
            ]
          },
          "url": {
            "urls": [
              {
                "display_url": "grok.com/download",
                "end": 23,
                "expanded_url": "http://grok.com/download",
                "start": 0,
                "url": "https://t.co/fqNKQSjjG9"
              }
            ]
          }
        },
        "id": "1720665183188922368",
        "name": "Grok",
        "profile_image_url": "https://pbs.twimg.com/profile_images/2057885623374290944/lmj0pawP_normal.jpg",
        "protected": false,
        "public_metrics": {
          "followers_count": 8807904,
          "following_count": 5,
          "like_count": 104,
          "listed_count": 7010,
          "media_count": 9049436,
          "tweet_count": 128981040
        },
        "url": "https://t.co/fqNKQSjjG9",
        "username": "grok",
        "verified": true
      },
      {
        "created_at": "2009-06-02T20:12:29.000Z",
        "description": "https://t.co/dDtDyVssfm",
        "entities": {
          "description": {
            "urls": [
              {
                "display_url": "Terafab.ai",
                "end": 23,
                "expanded_url": "http://Terafab.ai",
                "start": 0,
                "url": "https://t.co/dDtDyVssfm"
              }
            ]
          }
        },
        "id": "44196397",
        "name": "Elon Musk",
        "pinned_tweet_id": "2064187087184650253",
        "profile_image_url": "https://pbs.twimg.com/profile_images/2053244804520427520/m8mdWZCG_normal.jpg",
        "protected": false,
        "public_metrics": {
          "followers_count": 240273449,
          "following_count": 1354,
          "like_count": 234256,
          "listed_count": 169562,
          "media_count": 4541,
          "tweet_count": 104201
        },
        "username": "elonmusk",
        "verified": true
      }
    ]
  }
}